odoo10_addon_donation_recurring-10.0.1.0.0.99.dev10-py3.8-nspkg.pth
odoo/addons/donation_recurring/README.rst
odoo/addons/donation_recurring/__init__.py
odoo/addons/donation_recurring/__manifest__.py
odoo/addons/donation_recurring/demo/donation_recurring_demo.xml
odoo/addons/donation_recurring/i18n/de.po
odoo/addons/donation_recurring/i18n/donation_recurring.pot
odoo/addons/donation_recurring/i18n/fr.po
odoo/addons/donation_recurring/models/__init__.py
odoo/addons/donation_recurring/models/donation.py
odoo/addons/donation_recurring/static/description/icon.png
odoo/addons/donation_recurring/tests/__init__.py
odoo/addons/donation_recurring/tests/test_recurring_donations.py
odoo/addons/donation_recurring/views/donation.xml
odoo/addons/donation_recurring/wizard/__init__.py
odoo/addons/donation_recurring/wizard/donation_recurring_generate.py
odoo/addons/donation_recurring/wizard/donation_recurring_generate_view.xml
odoo10_addon_donation_recurring-10.0.1.0.0.99.dev10.dist-info/METADATA
odoo10_addon_donation_recurring-10.0.1.0.0.99.dev10.dist-info/WHEEL
odoo10_addon_donation_recurring-10.0.1.0.0.99.dev10.dist-info/namespace_packages.txt
odoo10_addon_donation_recurring-10.0.1.0.0.99.dev10.dist-info/top_level.txt
odoo10_addon_donation_recurring-10.0.1.0.0.99.dev10.dist-info/RECORD
